setup.py
django_shpaml_template_loader.egg-info/PKG-INFO
django_shpaml_template_loader.egg-info/SOURCES.txt
django_shpaml_template_loader.egg-info/dependency_links.txt
django_shpaml_template_loader.egg-info/top_level.txt
shpaml_loader/__init__.py
shpaml_loader/loaders.py
shpaml_loader/models.py
shpaml_loader/shpaml.py
shpaml_loader/utils.py