Metadata-Version: 1.0
Name: django-shpaml-template-loader
Version: 0.2.3
Summary: A Django template loader for loading and converting SHPAML markup to HTML
Home-page: http://bitbucket.org/jiaaro/django-shpaml-template-loader/
Author: Jim Robert
Author-email: UNKNOWN
License: BSD
Keywords: django shpaml
Platform: UNKNOWN
Classifier: License :: OSI Approved :: BSD License
Classifier: Programming Language :: Python
Classifier: Environment :: Web Environment
Classifier: Intended Audience :: Developers
Classifier: Operating System :: OS Independent
Classifier: Topic :: Internet :: WWW/HTTP
Classifier: Topic :: Utilities
